{"apo_pdb_id": "4r7t", "chain": "C", "fold": "train-1", "pocket_token_count": 19, "positive_count": 19, "masked_count": 0, "remapped_count": 0, "fraction_masked": 0.0, "labels": {"C_137": 1, "C_138": 1, "C_139": 1, "C_143": 1, "C_144": 1, "C_145": 1, "C_146": 1, "C_172": 1, "C_173": 1, "C_208": 1, "C_40": 1, "C_41": 1, "C_42": 1, "C_43": 1, "C_44": 1, "C_45": 1, "C_71": 1, "C_72": 1, "C_85": 1}, "generated_at": "2026-05-27T23:43:19.519222", "governance": "docs/scientific_governance/06_LABELING_RULES.md"}