{"apo_pdb_id": "5gmo", "chain": "A", "fold": "train-3", "pocket_token_count": 31, "positive_count": 31, "masked_count": 0, "remapped_count": 0, "fraction_masked": 0.0, "labels": {"A_10": 1, "A_11": 1, "A_12": 1, "A_123": 1, "A_124": 1, "A_125": 1, "A_126": 1, "A_13": 1, "A_14": 1, "A_163": 1, "A_167": 1, "A_192": 1, "A_193": 1, "A_194": 1, "A_195": 1, "A_210": 1, "A_211": 1, "A_212": 1, "A_34": 1, "A_38": 1, "A_56": 1, "A_58": 1, "A_59": 1, "A_80": 1, "A_81": 1, "A_82": 1, "A_83": 1, "A_84": 1, "A_9": 1, "A_94": 1, "A_98": 1}, "generated_at": "2026-05-27T23:43:21.226111", "governance": "docs/scientific_governance/06_LABELING_RULES.md"}