{"apo_pdb_id": "2i1w", "chain": "B", "fold": "train-1", "pocket_token_count": 20, "positive_count": 20, "masked_count": 0, "remapped_count": 0, "fraction_masked": 0.0, "labels": {"B_122": 1, "B_123": 1, "B_158": 1, "B_159": 1, "B_161": 1, "B_162": 1, "B_163": 1, "B_166": 1, "B_222": 1, "B_223": 1, "B_261": 1, "B_44": 1, "B_45": 1, "B_46": 1, "B_49": 1, "B_71": 1, "B_72": 1, "B_73": 1, "B_74": 1, "B_75": 1}, "generated_at": "2026-05-27T23:43:14.885551", "governance": "docs/scientific_governance/06_LABELING_RULES.md"}