{"apo_pdb_id": "2x47", "chain": "A", "fold": "test", "pocket_token_count": 26, "positive_count": 26, "masked_count": 0, "remapped_count": 0, "fraction_masked": 0.0, "labels": {"A_159": 1, "A_160": 1, "A_161": 1, "A_172": 1, "A_173": 1, "A_174": 1, "A_179": 1, "A_180": 1, "A_181": 1, "A_182": 1, "A_183": 1, "A_184": 1, "A_186": 1, "A_265": 1, "A_266": 1, "A_267": 1, "A_268": 1, "A_269": 1, "A_270": 1, "A_271": 1, "A_272": 1, "A_273": 1, "A_304": 1, "A_306": 1, "A_307": 1, "A_310": 1}, "generated_at": "2026-05-27T23:43:15.704414", "governance": "docs/scientific_governance/06_LABELING_RULES.md"}