{"apo_pdb_id": "5tsx", "chain": "B-F", "fold": "train-1", "pocket_token_count": 25, "positive_count": 0, "masked_count": 25, "remapped_count": 0, "fraction_masked": 1.0, "labels": {"B_169": -1, "B_172": -1, "B_173": -1, "B_179": -1, "B_182": -1, "B_183": -1, "B_37": -1, "B_38": -1, "B_41": -1, "F_105": -1, "F_106": -1, "F_107": -1, "F_130": -1, "F_50": -1, "F_53": -1, "F_54": -1, "F_56": -1, "F_57": -1, "F_63": -1, "F_66": -1, "F_67": -1, "F_69": -1, "F_70": -1, "F_73": -1, "F_74": -1}, "generated_at": "2026-05-27T23:43:22.212249", "governance": "docs/scientific_governance/06_LABELING_RULES.md"}